setupmeta/__init__.py
setupmeta/commands.py
setupmeta/content.py
setupmeta/hook.py
setupmeta/license.py
setupmeta/model.py
setupmeta/scm.py
setupmeta/versioning.py
setupmeta-3.8.0.dist-info/licenses/LICENSE
setupmeta-3.8.0.dist-info/METADATA
setupmeta-3.8.0.dist-info/WHEEL
setupmeta-3.8.0.dist-info/entry_points.txt
setupmeta-3.8.0.dist-info/top_level.txt
setupmeta-3.8.0.dist-info/zip-safe
setupmeta-3.8.0.dist-info/RECORD
